pygwb/__init__.py
pygwb/_version.py
pygwb/background.py
pygwb/baseline.py
pygwb/coherence.py
pygwb/constants.py
pygwb/delta_sigma_cut.py
pygwb/detector.py
pygwb/html.py
pygwb/network.py
pygwb/notch.py
pygwb/omega_spectra.py
pygwb/orfs.py
pygwb/parameters.py
pygwb/pe.py
pygwb/postprocessing.py
pygwb/preprocessing.py
pygwb/simulator.py
pygwb/spectral.py
pygwb/statistical_checks.py
pygwb/util.py
pygwb/workflow.py
pygwb-1.5.1.data/scripts/pygwb_combine
pygwb-1.5.1.data/scripts/pygwb_create_isotropic_workflow
pygwb-1.5.1.data/scripts/pygwb_dag
pygwb-1.5.1.data/scripts/pygwb_html
pygwb-1.5.1.data/scripts/pygwb_pe
pygwb-1.5.1.data/scripts/pygwb_pipe
pygwb-1.5.1.data/scripts/pygwb_simulate
pygwb-1.5.1.data/scripts/pygwb_stats
pygwb-1.5.1.dist-info/LICENSE
pygwb-1.5.1.dist-info/METADATA
pygwb-1.5.1.dist-info/WHEEL
pygwb-1.5.1.dist-info/top_level.txt
pygwb-1.5.1.dist-info/RECORD
