Metadata-Version: 2.1
Name: pygwb
Version: 1.5.1
Summary: Lighweight python stochastic gravitational-wave background analysis pipeline
Home-page: https://git.ligo.org/pygwb/pygwb
Author: Arianna Renzini, Sylvia Biscoveanu, Shivaraj Khandasamy, Kamiel Janssens, Max Lalleman, Katarina Martinovic, Andrew Matas, Patrick Meyers, Alba Romero, Colm Talbot, Leo Tsukada, Kevin Turbang
Author-email: arianna.renzini@ligo.org
License: MIT
Classifier: Programming Language :: Python :: 3.8
Classifier: Programming Language :: Python :: 3.9
Classifier: Programming Language :: Python :: 3.10
Classifier: Programming Language :: Python :: 3.11
Classifier: License :: OSI Approved :: MIT License
Classifier: Operating System :: OS Independent
Requires-Python: >=3.8
License-File: LICENSE
Requires-Dist: numpy
Requires-Dist: matplotlib
Requires-Dist: scipy <1.14.0,>=1.8.0
Requires-Dist: bilby >=1.4
Requires-Dist: gwpy >=3.0.4
Requires-Dist: astropy >=5.2
Requires-Dist: gwdetchar
Requires-Dist: gwsumm
Requires-Dist: pycondor
Requires-Dist: lalsuite >=7.3
Requires-Dist: loguru
Requires-Dist: json5
Requires-Dist: seaborn
Requires-Dist: pycbc
Provides-Extra: dev
Requires-Dist: pytest ; extra == 'dev'
